cardtool/__init__.py
cardtool/card/__init__.py
cardtool/card/bootstrap.py
cardtool/card/cipher.py
cardtool/card/data.py
cardtool/card/dump.py
cardtool/card/model.py
cardtool/card/pin.py
cardtool/card/tags.py
cardtool/command/__init__.py
cardtool/command/gen_card.py
cardtool/command/main_group.py
cardtool/command/tr31_decrypt.py
cardtool/config/__init__.py
cardtool/config/card-config.json
cardtool/config/load.py
cardtool/dukpt/__init__.py
cardtool/dukpt/cipher.py
cardtool/dukpt/key.py
cardtool/dukpt/key_type.py
cardtool/dukpt/key_variant.py
cardtool/log/__init__.py
cardtool/log/logger.py
cardtool/tr31/__init__.py
cardtool/tr31/decrypt.py
cardtool/tr31/key_block.py
cardtool/util/__init__.py
cardtool/util/common.py
cardtool/util/model.py
cardtool/util/serialize.py
cardtool/validation/__init__.py
cardtool/validation/command.py
cardtool/validation/rules.py
cardtool-0.0.6.dist-info/LICENSE
cardtool-0.0.6.dist-info/METADATA
cardtool-0.0.6.dist-info/WHEEL
cardtool-0.0.6.dist-info/entry_points.txt
cardtool-0.0.6.dist-info/top_level.txt
cardtool-0.0.6.dist-info/RECORD
