Metadata-Version: 2.1
Name: cardtool
Version: 0.0.6
Summary: An encrypted card generator tool
Author-email: Daniel Aucatoma <d4n13l.4lf4@gmail.com>
Keywords: DUKPT,credit,card,tool
Classifier: Programming Language :: Python :: 3
Classifier: License :: OSI Approved :: MIT License
Requires-Python: >=3.9
License-File: LICENSE
Requires-Dist: click ==8.1.3
Requires-Dist: pycryptodome ==3.18.0
Requires-Dist: PyYAML ==6.0
Requires-Dist: loguru ==0.7.0
Requires-Dist: jsonschema ==4.17.3
Requires-Dist: pydash ==7.0.4
Requires-Dist: ber-tlv ==0.0.6
Requires-Dist: simplejson ==3.19.1
Requires-Dist: dill ==0.3.6
Requires-Dist: toolz ==0.12.0
Requires-Dist: pycountry ==22.3.5
